<?xml version = '1.0' encoding = 'UTF-8'?>
<TableProxyOraclev12c class="oracle.dbtools.crest.model.design.storage.oracle.v12c.TableProxyOraclev12c" name="GRADO" directorySegmentName="seg_0" id="FC74F828-1E49-A6AF-357E-85B496D20F13">
<createdBy>alumno</createdBy>
<createdTime>2022-11-02 08:26:21 UTC</createdTime>
<ownerDesignName>NOVIEMBRE</ownerDesignName>
<schemaObject>71389D57-F2E5-8229-E406-76EAF2C3DBD6</schemaObject>
<logging>YES</logging>
<partitionedRowMovement>DISABLE</partitionedRowMovement>
<segment>14A0F82D-8838-33C0-F2F5-32F2FC429117</segment>
<tableSpace>45E52D67-07C1-10D8-052F-9259827A6DB7</tableSpace>
<temporaryChanged>false</temporaryChanged>
<accessDriverType>oracle_loader</accessDriverType>
<rejectLimit></rejectLimit>
<inMemory>NO</inMemory>
<columnProxies itemClass="oracle.dbtools.crest.model.design.storage.oracle.v12c.ColumnProxyOraclev12c">
<ColumnProxy name="NOMBRE" id="0F722BF3-589E-F054-F708-72DDCDB2137B">
<createdBy>alumno</createdBy>
<createdTime>2022-11-02 08:26:21 UTC</createdTime>
<ownerDesignName>NOVIEMBRE</ownerDesignName>
</ColumnProxy>
<ColumnProxy name="CREDITOS_TOTALES" id="B821EE92-0252-E8C7-0463-15A44B3591B9">
<createdBy>alumno</createdBy>
<createdTime>2022-11-02 08:26:21 UTC</createdTime>
<ownerDesignName>NOVIEMBRE</ownerDesignName>
</ColumnProxy>
<ColumnProxy name="CODIGO" id="CADF2DCE-A5D4-A850-0210-568B19976FCD">
<createdBy>alumno</createdBy>
<createdTime>2022-11-02 08:26:21 UTC</createdTime>
<ownerDesignName>NOVIEMBRE</ownerDesignName>
</ColumnProxy>
</columnProxies>
<primaryKeys>
<PrimaryKey class="oracle.dbtools.crest.model.design.storage.oracle.v10g.PKProxyOraclev10g" name="GRADO_PK" id="CD8090C2-B5E0-397D-1BD7-43EC86873AFA">
<createdBy>alumno</createdBy>
<createdTime>2022-11-02 08:26:21 UTC</createdTime>
<ownerDesignName>NOVIEMBRE</ownerDesignName>
<schemaObject>71389D57-F2E5-8229-E406-76EAF2C3DBD6</schemaObject>
<segment>67C690AE-A82B-67DB-C5EB-6DE9E30E2639</segment>
<tableSpace>45E52D67-07C1-10D8-052F-9259827A6DB7</tableSpace>
<indexSegment>67C690AE-A82B-67DB-C5EB-6DE9E30E2639</indexSegment>
<indexSort>SORTED</indexSort>
<usingIndex>BY INDEX NAME</usingIndex>
</PrimaryKey>
</primaryKeys>
</TableProxyOraclev12c>